solcast/__init__.py
solcast/dependencies.py
solcast/grammar.py
solcast/main.py
solcast/nodes.py
py_solc_ast-1.2.9.dist-info/LICENSE
py_solc_ast-1.2.9.dist-info/METADATA
py_solc_ast-1.2.9.dist-info/WHEEL
py_solc_ast-1.2.9.dist-info/top_level.txt
py_solc_ast-1.2.9.dist-info/RECORD
