Metadata-Version: 2.1
Name: py-solc-ast
Version: 1.2.9
Summary: A tool for exploring the abstract syntax tree generated by solc.
Home-page: https://github.com/iamdefinitelyahuman/py-solc-ast
Author: Ben Hauser
Author-email: ben@hauser.id
License: MIT
Keywords: ethereum,solidity,solc,ast
Platform: UNKNOWN
Classifier: Development Status :: 5 - Production/Stable
Classifier: Intended Audience :: Developers
Classifier: License :: OSI Approved :: MIT License
Classifier: Natural Language :: English
Classifier: Programming Language :: Python :: 3
Classifier: Programming Language :: Python :: 3.6
Classifier: Programming Language :: Python :: 3.7
Classifier: Programming Language :: Python :: 3.8
Classifier: Programming Language :: Python :: 3.9
Requires-Python: >=3.6, <4
